<?xml version="1.0" encoding="utf-8" ?>
<dwsync>
<file name="affix.js" server="//WCGSERVER/Interactive Server/VAULT/" local="130408398616171431" remote="130408398610000000" Dst="2" />
<file name="alert.js" server="//WCGSERVER/Interactive Server/VAULT/" local="130408398612521222" remote="130408398610000000" Dst="2" />
<file name="button.js" server="//WCGSERVER/Interactive Server/VAULT/" local="130408398612971248" remote="130408398610000000" Dst="2" />
<file name="carousel.js" server="//WCGSERVER/Interactive Server/VAULT/" local="130408398616731463" remote="130408398610000000" Dst="2" />
<file name="collapse.js" server="//WCGSERVER/Interactive Server/VAULT/" local="130408398617051481" remote="130408398610000000" Dst="2" />
<file name="dropdown.js" server="//WCGSERVER/Interactive Server/VAULT/" local="130408398611451161" remote="130408398610000000" Dst="2" />
<file name="modal.js" server="//WCGSERVER/Interactive Server/VAULT/" local="130408398611621171" remote="130408398610000000" Dst="2" />
<file name="popover.js" server="//WCGSERVER/Interactive Server/VAULT/" local="130408398615801410" remote="130408398610000000" Dst="2" />
<file name="scrollspy.js" server="//WCGSERVER/Interactive Server/VAULT/" local="130408398613501278" remote="130408398610000000" Dst="2" />
<file name="tab.js" server="//WCGSERVER/Interactive Server/VAULT/" local="130408398614411330" remote="130408398610000000" Dst="2" />
<file name="tooltip.js" server="//WCGSERVER/Interactive Server/VAULT/" local="130408398614941360" remote="130408398610000000" Dst="2" />
<file name="transition.js" server="//WCGSERVER/Interactive Server/VAULT/" local="130408398613861299" remote="130408398610000000" Dst="2" />
</dwsync>